{"list_contest_success": true, "contest_list": "| # |       PROBLEM        | PASSED |    LIMIT    |          IO           |\n|---|----------------------|--------|-------------|-----------------------|\n| A |   Sonya and Hotels   | 10134  | 1 s, 256 MB | standard input/output |\n| B | Sonya and Exhibition |  8429  | 1 s, 256 MB | standard input/output |\n| C |   Sonya and Robots   |  6986  | 1 s, 256 MB | standard input/output |\n| D |   Sonya and Matrix   |  1332  | 2 s, 256 MB | standard input/output |\n| E | Sonya and Ice Cream  |  888   | 2 s, 256 MB | standard input/output |\n| F | Sonya and Bitwise OR |  546   | 4 s, 512 MB | standard input/output |\n", "problem_sub_id": "b", "submit_success": false, "submit_output": "Submit CONTEST 1004, problem b\nCurrent user: tomas_fang\nSubmitted\n      #: 215847854\n   when: 2023-07-27 09:35\n   prob: B - Sonya and Exhibition\n   lang: GNU C++14\n\n\u001b[1A status: Unknown\n   time: 0 ms\n memory: 0 B\n\u001b[7A      #: 215847854\n   when: 2023-07-27 09:35\n   prob: B - Sonya and Exhibition\n   lang: GNU C++14\n                 \n\u001b[1A status: Running on test 2\n   time: 0 ms\n memory: 0 B\n\u001b[7A      #: 215847854\n   when: 2023-07-27 09:35\n   prob: B - Sonya and Exhibition\n   lang: GNU C++14\n                           \n\u001b[1A status: Accepted\n   time: 15 ms\n memory: 0 B\n", "status": "Accepted", "cpu_time": "15 ms", "memory": "0 B"}
