{"list_contest_success": true, "contest_list": "| # |        PROBLEM         | PASSED |    LIMIT    |          IO           |\n|---|------------------------|--------|-------------|-----------------------|\n| A |   Display The Number   |  9934  | 1 s, 256 MB | standard input/output |\n| B |   Infinite Prefixes    |  3038  | 2 s, 256 MB | standard input/output |\n| C |   Obtain The String    |  3675  | 1 s, 256 MB | standard input/output |\n| D |       Same GCDs        |  1783  | 2 s, 256 MB | standard input/output |\n| E | Permutation Separation |  404   | 2 s, 256 MB | standard input/output |\n| F |      Good Contest      |   52   | 3 s, 256 MB | standard input/output |\n", "problem_sub_id": "e", "submit_success": false, "submit_output": "Submit CONTEST 1295, problem e\nCurrent user: tomas_fang\nSubmitted\n      #: 213088988\n   when: 2023-07-10 09:16\n   prob: E - Permutation Separation\n   lang: GNU C++14\n\n\u001b[1A status: Unknown\n   time: 0 ms\n memory: 0 B\n\u001b[7A      #: 213088988\n   when: 2023-07-10 09:16\n   prob: E - Permutation Separation\n   lang: GNU C++14\n                 \n\u001b[1A status: Unknown\n   time: 0 ms\n memory: 0 B\n\u001b[7A      #: 213088988\n   when: 2023-07-10 09:16\n   prob: E - Permutation Separation\n   lang: GNU C++14\n                 \n\u001b[1A status: Accepted\n   time: 826 ms\n memory: 27.73 MB\n", "status": "Accepted", "cpu_time": "826 ms", "memory": "27.73 MB"}
