{"list_contest_success": true, "contest_list": "| # |         PROBLEM         | PASSED |    LIMIT    |          IO           |\n|---|-------------------------|--------|-------------|-----------------------|\n| A |     NP-Hard Problem     |  7225  | 2 s, 256 MB | standard input/output |\n| B |     Remainders Game     |  3317  | 1 s, 256 MB | standard input/output |\n| C | The Values You Can Make |  3051  | 2 s, 256 MB | standard input/output |\n| D |   Dividing Kingdom II   |  798   | 6 s, 256 MB | standard input/output |\n| E |           TOF           |  292   | 1 s, 256 MB | standard input/output |\n", "problem_sub_id": "d", "submit_success": false, "submit_output": "Submit CONTEST 687, problem d\nCurrent user: tomas_fang\nSubmitted\n      #: 216375824\n   when: 2023-07-29 23:00\n   prob: D - Dividing Kingdom II\n   lang: GNU C++14\n\n\u001b[1A status: Unknown\n   time: 0 ms\n memory: 0 B\n\u001b[7A      #: 216375824\n   when: 2023-07-29 23:00\n   prob: D - Dividing Kingdom II\n   lang: GNU C++14\n                 \n\u001b[1A status: Running on test 1\n   time: 0 ms\n memory: 0 B\n\u001b[7A      #: 216375824\n   when: 2023-07-29 23:00\n   prob: D - Dividing Kingdom II\n   lang: GNU C++14\n                           \n\u001b[1A status: Running on test 1\n   time: 0 ms\n memory: 0 B\n\u001b[7A      #: 216375824\n   when: 2023-07-29 23:00\n   prob: D - Dividing Kingdom II\n   lang: GNU C++14\n                           \n\u001b[1A status: Running on test 2\n   time: 0 ms\n memory: 0 B\n\u001b[7A      #: 216375824\n   when: 2023-07-29 23:00\n   prob: D - Dividing Kingdom II\n   lang: GNU C++14\n                           \n\u001b[1A status: Running on test 2\n   time: 0 ms\n memory: 0 B\n\u001b[7A      #: 216375824\n   when: 2023-07-29 23:00\n   prob: D - Dividing Kingdom II\n   lang: GNU C++14\n                           \n\u001b[1A status: Running on test 2\n   time: 0 ms\n memory: 0 B\n\u001b[7A      #: 216375824\n   when: 2023-07-29 23:00\n   prob: D - Dividing Kingdom II\n   lang: GNU C++14\n                           \n\u001b[1A status: Running on test 2\n   time: 0 ms\n memory: 0 B\n\u001b[7A      #: 216375824\n   when: 2023-07-29 23:00\n   prob: D - Dividing Kingdom II\n   lang: GNU C++14\n                           \n\u001b[1A status: Running on test 3\n   time: 0 ms\n memory: 0 B\n\u001b[7A      #: 216375824\n   when: 2023-07-29 23:00\n   prob: D - Dividing Kingdom II\n   lang: GNU C++14\n                           \n\u001b[1A status: Running on test 6\n   time: 0 ms\n memory: 0 B\n\u001b[7A      #: 216375824\n   when: 2023-07-29 23:00\n   prob: D - Dividing Kingdom II\n   lang: GNU C++14\n                           \n\u001b[1A status: Running on test 6\n   time: 0 ms\n memory: 0 B\n\u001b[7A      #: 216375824\n   when: 2023-07-29 23:00\n   prob: D - Dividing Kingdom II\n   lang: GNU C++14\n                           \n\u001b[1A status: Running on test 6\n   time: 0 ms\n memory: 0 B\n\u001b[7A      #: 216375824\n   when: 2023-07-29 23:00\n   prob: D - Dividing Kingdom II\n   lang: GNU C++14\n                           \n\u001b[1A status: Running on test 6\n   time: 0 ms\n memory: 0 B\n\u001b[7A      #: 216375824\n   when: 2023-07-29 23:00\n   prob: D - Dividing Kingdom II\n   lang: GNU C++14\n                           \n\u001b[1A status: Running on test 6\n   time: 0 ms\n memory: 0 B\n\u001b[7A      #: 216375824\n   when: 2023-07-29 23:00\n   prob: D - Dividing Kingdom II\n   lang: GNU C++14\n                           \n\u001b[1A status: Running on test 6\n   time: 0 ms\n memory: 0 B\n\u001b[7A      #: 216375824\n   when: 2023-07-29 23:00\n   prob: D - Dividing Kingdom II\n   lang: GNU C++14\n                           \n\u001b[1A status: Running on test 15\n   time: 0 ms\n memory: 0 B\n\u001b[7A      #: 216375824\n   when: 2023-07-29 23:00\n   prob: D - Dividing Kingdom II\n   lang: GNU C++14\n                            \n\u001b[1A status: Running on test 15\n   time: 0 ms\n memory: 0 B\n\u001b[7A      #: 216375824\n   when: 2023-07-29 23:00\n   prob: D - Dividing Kingdom II\n   lang: GNU C++14\n                            \n\u001b[1A status: Running on test 15\n   time: 0 ms\n memory: 0 B\n\u001b[7A      #: 216375824\n   when: 2023-07-29 23:00\n   prob: D - Dividing Kingdom II\n   lang: GNU C++14\n                            \n\u001b[1A status: Running on test 15\n   time: 0 ms\n memory: 0 B\n\u001b[7A      #: 216375824\n   when: 2023-07-29 23:00\n   prob: D - Dividing Kingdom II\n   lang: GNU C++14\n                            \n\u001b[1A status: Running on test 16\n   time: 0 ms\n memory: 0 B\n\u001b[7A      #: 216375824\n   when: 2023-07-29 23:00\n   prob: D - Dividing Kingdom II\n   lang: GNU C++14\n                            \n\u001b[1A status: Running on test 16\n   time: 0 ms\n memory: 0 B\n\u001b[7A      #: 216375824\n   when: 2023-07-29 23:00\n   prob: D - Dividing Kingdom II\n   lang: GNU C++14\n                            \n\u001b[1A status: Running on test 31\n   time: 0 ms\n memory: 0 B\n\u001b[7A      #: 216375824\n   when: 2023-07-29 23:00\n   prob: D - Dividing Kingdom II\n   lang: GNU C++14\n                            \n\u001b[1A status: Running on test 31\n   time: 0 ms\n memory: 0 B\n\u001b[7A      #: 216375824\n   when: 2023-07-29 23:00\n   prob: D - Dividing Kingdom II\n   lang: GNU C++14\n                            \n\u001b[1A status: Running on test 40\n   time: 0 ms\n memory: 0 B\n\u001b[7A      #: 216375824\n   when: 2023-07-29 23:00\n   prob: D - Dividing Kingdom II\n   lang: GNU C++14\n                            \n\u001b[1A status: Running on test 40\n   time: 0 ms\n memory: 0 B\n\u001b[7A      #: 216375824\n   when: 2023-07-29 23:00\n   prob: D - Dividing Kingdom II\n   lang: GNU C++14\n                            \n\u001b[1A status: Running on test 43\n   time: 0 ms\n memory: 0 B\n\u001b[7A      #: 216375824\n   when: 2023-07-29 23:00\n   prob: D - Dividing Kingdom II\n   lang: GNU C++14\n                            \n\u001b[1A status: Running on test 43\n   time: 0 ms\n memory: 0 B\n\u001b[7A      #: 216375824\n   when: 2023-07-29 23:00\n   prob: D - Dividing Kingdom II\n   lang: GNU C++14\n                            \n\u001b[1A status: Running on test 43\n   time: 0 ms\n memory: 0 B\n\u001b[7A      #: 216375824\n   when: 2023-07-29 23:00\n   prob: D - Dividing Kingdom II\n   lang: GNU C++14\n                            \n\u001b[1A status: Running on test 43\n   time: 0 ms\n memory: 0 B\n\u001b[7A      #: 216375824\n   when: 2023-07-29 23:00\n   prob: D - Dividing Kingdom II\n   lang: GNU C++14\n                            \n\u001b[1A status: Running on test 47\n   time: 0 ms\n memory: 0 B\n\u001b[7A      #: 216375824\n   when: 2023-07-29 23:00\n   prob: D - Dividing Kingdom II\n   lang: GNU C++14\n                            \n\u001b[1A status: Running on test 47\n   time: 0 ms\n memory: 0 B\n\u001b[7A      #: 216375824\n   when: 2023-07-29 23:00\n   prob: D - Dividing Kingdom II\n   lang: GNU C++14\n                            \n\u001b[1A status: Running on test 50\n   time: 0 ms\n memory: 0 B\n\u001b[7A      #: 216375824\n   when: 2023-07-29 23:00\n   prob: D - Dividing Kingdom II\n   lang: GNU C++14\n                            \n\u001b[1A status: Running on test 50\n   time: 0 ms\n memory: 0 B\n\u001b[7A      #: 216375824\n   when: 2023-07-29 23:00\n   prob: D - Dividing Kingdom II\n   lang: GNU C++14\n                            \n\u001b[1A status: Running on test 54\n   time: 0 ms\n memory: 0 B\n\u001b[7A      #: 216375824\n   when: 2023-07-29 23:00\n   prob: D - Dividing Kingdom II\n   lang: GNU C++14\n                            \n\u001b[1A status: Running on test 54\n   time: 0 ms\n memory: 0 B\n\u001b[7A      #: 216375824\n   when: 2023-07-29 23:00\n   prob: D - Dividing Kingdom II\n   lang: GNU C++14\n                            \n\u001b[1A status: Running on test 54\n   time: 0 ms\n memory: 0 B\n\u001b[7A      #: 216375824\n   when: 2023-07-29 23:00\n   prob: D - Dividing Kingdom II\n   lang: GNU C++14\n                            \n\u001b[1A status: Running on test 54\n   time: 0 ms\n memory: 0 B\n\u001b[7A      #: 216375824\n   when: 2023-07-29 23:00\n   prob: D - Dividing Kingdom II\n   lang: GNU C++14\n                            \n\u001b[1A status: Running on test 65\n   time: 0 ms\n memory: 0 B\n\u001b[7A      #: 216375824\n   when: 2023-07-29 23:00\n   prob: D - Dividing Kingdom II\n   lang: GNU C++14\n                            \n\u001b[1A status: Running on test 65\n   time: 0 ms\n memory: 0 B\n\u001b[7A      #: 216375824\n   when: 2023-07-29 23:00\n   prob: D - Dividing Kingdom II\n   lang: GNU C++14\n                            \n\u001b[1A status: Running on test 66\n   time: 0 ms\n memory: 0 B\n\u001b[7A      #: 216375824\n   when: 2023-07-29 23:00\n   prob: D - Dividing Kingdom II\n   lang: GNU C++14\n                            \n\u001b[1A status: Running on test 66\n   time: 0 ms\n memory: 0 B\n\u001b[7A      #: 216375824\n   when: 2023-07-29 23:00\n   prob: D - Dividing Kingdom II\n   lang: GNU C++14\n                            \n\u001b[1A status: Running on test 66\n   time: 0 ms\n memory: 0 B\n\u001b[7A      #: 216375824\n   when: 2023-07-29 23:00\n   prob: D - Dividing Kingdom II\n   lang: GNU C++14\n                            \n\u001b[1A status: Running on test 66\n   time: 0 ms\n memory: 0 B\n\u001b[7A      #: 216375824\n   when: 2023-07-29 23:00\n   prob: D - Dividing Kingdom II\n   lang: GNU C++14\n                            \n\u001b[1A status: Running on test 66\n   time: 0 ms\n memory: 0 B\n\u001b[7A      #: 216375824\n   when: 2023-07-29 23:00\n   prob: D - Dividing Kingdom II\n   lang: GNU C++14\n                            \n\u001b[1A status: Running on test 66\n   time: 0 ms\n memory: 0 B\n\u001b[7A      #: 216375824\n   when: 2023-07-29 23:00\n   prob: D - Dividing Kingdom II\n   lang: GNU C++14\n                            \n\u001b[1A status: Running on test 69\n   time: 0 ms\n memory: 0 B\n\u001b[7A      #: 216375824\n   when: 2023-07-29 23:00\n   prob: D - Dividing Kingdom II\n   lang: GNU C++14\n                            \n\u001b[1A status: Running on test 69\n   time: 0 ms\n memory: 0 B\n\u001b[7A      #: 216375824\n   when: 2023-07-29 23:00\n   prob: D - Dividing Kingdom II\n   lang: GNU C++14\n                            \n\u001b[1A status: Running on test 81\n   time: 0 ms\n memory: 0 B\n\u001b[7A      #: 216375824\n   when: 2023-07-29 23:00\n   prob: D - Dividing Kingdom II\n   lang: GNU C++14\n                            \n\u001b[1A status: Running on test 81\n   time: 0 ms\n memory: 0 B\n\u001b[7A      #: 216375824\n   when: 2023-07-29 23:00\n   prob: D - Dividing Kingdom II\n   lang: GNU C++14\n                            \n\u001b[1A status: Running on test 81\n   time: 0 ms\n memory: 0 B\n\u001b[7A      #: 216375824\n   when: 2023-07-29 23:00\n   prob: D - Dividing Kingdom II\n   lang: GNU C++14\n                            \n\u001b[1A status: Running on test 81\n   time: 0 ms\n memory: 0 B\n\u001b[7A      #: 216375824\n   when: 2023-07-29 23:00\n   prob: D - Dividing Kingdom II\n   lang: GNU C++14\n                            \n\u001b[1A status: Running on test 87\n   time: 0 ms\n memory: 0 B\n\u001b[7A      #: 216375824\n   when: 2023-07-29 23:00\n   prob: D - Dividing Kingdom II\n   lang: GNU C++14\n                            \n\u001b[1A status: Running on test 87\n   time: 0 ms\n memory: 0 B\n\u001b[7A      #: 216375824\n   when: 2023-07-29 23:00\n   prob: D - Dividing Kingdom II\n   lang: GNU C++14\n                            \n\u001b[1A status: Running on test 87\n   time: 0 ms\n memory: 0 B\n\u001b[7A      #: 216375824\n   when: 2023-07-29 23:00\n   prob: D - Dividing Kingdom II\n   lang: GNU C++14\n                            \n\u001b[1A status: Accepted\n   time: 4352 ms\n memory: 7.62 MB\n", "status": "Accepted", "cpu_time": "4352 ms", "memory": "7.62 MB"}
