{"list_contest_success": true, "contest_list": "| # |           PROBLEM           | PASSED |    LIMIT    |          IO           |\n|---|-----------------------------|--------|-------------|-----------------------|\n| A | Comparing Two Long Integers |  2135  | 2 s, 256 MB | standard input/output |\n| B |      Dinner with Emma       |  2633  | 1 s, 256 MB | standard input/output |\n| C |        The Labyrinth        |  1144  | 1 s, 256 MB | standard input/output |\n| D |   Longest k-Good Segment    |  1034  | 1 s, 256 MB | standard input/output |\n| E |      Sum of Remainders      |  212   | 2 s, 256 MB | standard input/output |\n| F |      Expensive Strings      |   20   | 6 s, 512 MB | standard input/output |\n", "problem_sub_id": "d", "submit_success": false, "submit_output": "Submit CONTEST 616, problem d\nCurrent user: tomas_fang\nSubmitted\n      #: 216367015\n   when: 2023-07-29 20:44\n   prob: D - Longest k-Good Segment\n   lang: GNU C++14\n\n\u001b[1A status: Unknown\n   time: 0 ms\n memory: 0 B\n\u001b[7A      #: 216367015\n   when: 2023-07-29 20:44\n   prob: D - Longest k-Good Segment\n   lang: GNU C++14\n                 \n\u001b[1A status: Unknown\n   time: 0 ms\n memory: 0 B\n\u001b[7A      #: 216367015\n   when: 2023-07-29 20:44\n   prob: D - Longest k-Good Segment\n   lang: GNU C++14\n                 \n\u001b[1A status: Running on test 6\n   time: 0 ms\n memory: 0 B\n\u001b[7A      #: 216367015\n   when: 2023-07-29 20:44\n   prob: D - Longest k-Good Segment\n   lang: GNU C++14\n                           \n\u001b[1A status: Running on test 6\n   time: 0 ms\n memory: 0 B\n\u001b[7A      #: 216367015\n   when: 2023-07-29 20:44\n   prob: D - Longest k-Good Segment\n   lang: GNU C++14\n                           \n\u001b[1A status: Accepted\n   time: 124 ms\n memory: 5.76 MB\n", "status": "Accepted", "cpu_time": "124 ms", "memory": "5.76 MB"}
